CHANGES.rst
COPYING
MANIFEST.in
Makefile
README.rst
bootstrap-buildout.py
bootstrap-virtualenv.in
bootstrap-virtualenv.py
buildout.cfg
ez_setup.py
requirements-dev.in
requirements-dev.txt
requirements-test.in
requirements-test.txt
requirements.in
requirements.txt
setup.cfg
setup.py
smtptest.py
tox.ini
xoauth2relay.tac
docs/Makefile
docs/changelogs.rst
docs/cli.rst
docs/conf.py
docs/index.rst
docs/intro.rst
docs/make.bat
docs/locale/en/LC_MESSAGES/changelogs.po
docs/locale/en/LC_MESSAGES/cli.po
docs/locale/en/LC_MESSAGES/index.po
docs/locale/en/LC_MESSAGES/intro.po
docs/locale/ko/LC_MESSAGES/changelogs.po
docs/locale/ko/LC_MESSAGES/cli.po
docs/locale/ko/LC_MESSAGES/index.po
docs/locale/ko/LC_MESSAGES/intro.po
docs/locale/pot/changelogs.pot
docs/locale/pot/cli.pot
docs/locale/pot/index.pot
docs/locale/pot/intro.pot
docs/static/empty.css
mete0r.xoauth2relay.egg-info/PKG-INFO
mete0r.xoauth2relay.egg-info/SOURCES.txt
mete0r.xoauth2relay.egg-info/dependency_links.txt
mete0r.xoauth2relay.egg-info/entry_points.txt
mete0r.xoauth2relay.egg-info/not-zip-safe
mete0r.xoauth2relay.egg-info/requires.txt
mete0r.xoauth2relay.egg-info/top_level.txt
mete0r_xoauth2relay/__init__.py
mete0r_xoauth2relay/__main__.py
mete0r_xoauth2relay/cli.py
mete0r_xoauth2relay/oauth2.py
mete0r_xoauth2relay/twistedapp.py
mete0r_xoauth2relay/wsgi.py
mete0r_xoauth2relay/xoauth2.py
mete0r_xoauth2relay/locale/mete0r.xoauth2relay.pot
mete0r_xoauth2relay/locale/en/LC_MESSAGES/mete0r.xoauth2relay.po
mete0r_xoauth2relay/locale/ko/LC_MESSAGES/mete0r.xoauth2relay.po
mete0r_xoauth2relay/recipe/__init__.py
mete0r_xoauth2relay/tests/__init__.py
mete0r_xoauth2relay/tests/test_app.py
mete0r_xoauth2relay/tests/utils.py
mete0r_xoauth2relay/tests/fixtures/__init__.py
mete0r_xoauth2relay/tests/layers/__init__.py
virtualenv_support/README.rst